painlessdb/__init__.py
painlessdb/db.py
painlessdb/core/__init__.py
painlessdb/core/data.py
painlessdb/core/exceptions.py
painlessdb/core/schema.py
painlessdb/core/management/__init__.py
painlessdb/core/management/commands.py
painlessdb/utils/__init__.py
painlessdb/utils/converter.py
painlessdb/utils/dataTools.py
tests/__init__.py
tests/test_db.py
tests/test_dtypes.py
tests/test_exceptions.py
tests/test_schema.py
painlessdb-0.1.1.dist-info/LICENSE.md
painlessdb-0.1.1.dist-info/METADATA
painlessdb-0.1.1.dist-info/WHEEL
painlessdb-0.1.1.dist-info/entry_points.txt
painlessdb-0.1.1.dist-info/top_level.txt
painlessdb-0.1.1.dist-info/RECORD
