Metadata-Version: 2.1
Name: painlessdb
Version: 0.1.1
Summary: A Painless Simple Way To Create Schema and Do Database Operations Quickly In Python.
Home-page: https://github.com/AidenEllis/PainlessDB
Author: Aiden Ellis
Author-email: itsaidenellis@protonmail.com
License: MIT
Project-URL: Github, https://github.com/AidenEllis/PainlessDB
Project-URL: Documentation, https://github.com/AidenEllis/PainlessDB/tree/main/docs
Project-URL: Issue tracker, https://github.com/AidenEllis/PainlessDB/issues
Keywords: painlessdb,db,database,PainlessDB,AidenEllis,pldb
Platform: UNKNOWN
Classifier: Development Status :: 5 - Production/Stable
Classifier: Programming Language :: Python :: 3
Classifier: Operating System :: OS Independent
Classifier: License :: OSI Approved :: MIT License
Classifier: Natural Language :: English
Classifier: Intended Audience :: Developers
Classifier: Topic :: Software Development :: Libraries
Classifier: Topic :: Software Development :: Libraries :: Python Modules
Classifier: Topic :: Utilities
License-File: LICENSE.md
Requires-Dist: certifi (==2021.10.8)
Requires-Dist: ujson
Requires-Dist: wincertstore (==0.2)
